{"offers": [{"itemId": "188530139:4861248990:27861942915:730", "amount": 1, "inMarket": false, "lockedStatus": false, "title": "Souvenir MAG-7 | Core Breach (Factory New)", "status": "active", "dm_discount": 74, "dm_price": {"value": 40.61, "currency": "USD", "cValue": null, "cCurrency": null}, "sm_price": null, "steam_name_id": "176007989", "histogram": null}, {"itemId": "519977179:4578736725:27330520657:730", "amount": 1, "inMarket": false, "lockedStatus": false, "title": "M4A4 | Red DDPAT (Battle-Scarred)", "status": "active", "dm_discount": 49, "dm_price": {"value": 24.0, "currency": "USD", "cValue": null, "cCurrency": null}, "sm_price": null, "steam_name_id": "176262818", "histogram": null}, {"itemId": "188530170:2972581028:27099491063:730", "amount": 1, "inMarket": false, "lockedStatus": false, "title": "\u2605 StatTrak\u2122 Navaja Knife | Crimson Web (Well-Worn)", "status": "active", "dm_discount": 35, "dm_price": {"value": 91.15, "currency": "USD", "cValue": null, "cCurrency": null}, "sm_price": null, "steam_name_id": "176002889", "histogram": null}, {"itemId": "188530139:316125834:27571037241:730", "amount": 1, "inMarket": false, "lockedStatus": false, "title": "\u2605 Gut Knife | Blue Steel (Field-Tested)", "status": "active", "dm_discount": 30, "dm_price": {"value": 70.99, "currency": "USD", "cValue": null, "cCurrency": null}, "sm_price": null, "steam_name_id": "1321782", "histogram": null}, {"itemId": "188530170:638261962:25843601743:730", "amount": 1, "inMarket": false, "lockedStatus": false, "title": "StatTrak\u2122 XM1014 | Tranquility (Well-Worn)", "status": "active", "dm_discount": 27, "dm_price": {"value": 11.17, "currency": "USD", "cValue": null, "cCurrency": null}, "sm_price": null, "steam_name_id": "23861468", "histogram": null}, {"itemId": "0:310778984:26678034212:730", "amount": 1, "inMarket": false, "lockedStatus": false, "title": "M249 | Jungle DDPAT (Factory New)", "status": "active", "dm_discount": 27, "dm_price": {"value": 12.17, "currency": "USD", "cValue": null, "cCurrency": null}, "sm_price": null, "steam_name_id": "1547199", "histogram": null}, {"itemId": "188530721:346207471:27569193305:730", "amount": 1, "inMarket": false, "lockedStatus": false, "title": "\u2605 StatTrak\u2122 Gut Knife | Night (Battle-Scarred)", "status": "active", "dm_discount": 27, "dm_price": {"value": 74.74, "currency": "USD", "cValue": null, "cCurrency": null}, "sm_price": null, "steam_name_id": "9646740", "histogram": null}, {"itemId": "188530170:4961140636:27845533500:730", "amount": 1, "inMarket": false, "lockedStatus": false, "title": "StatTrak\u2122 Five-SeveN | Case Hardened (Factory New)", "status": "active", "dm_discount": 26, "dm_price": {"value": 36.61, "currency": "USD", "cValue": null, "cCurrency": null}, "sm_price": null, "steam_name_id": "1927237", "histogram": null}, {"itemId": "188530170:4961044368:27276843148:730", "amount": 1, "inMarket": false, "lockedStatus": false, "title": "\u2605 StatTrak\u2122 Falchion Knife | Scorched (Well-Worn)", "status": "active", "dm_discount": 26, "dm_price": {"value": 83.0, "currency": "USD", "cValue": null, "cCurrency": null}, "sm_price": null, "steam_name_id": "49715527", "histogram": null}, {"itemId": "188530170:5097161476:27867921135:730", "amount": 1, "inMarket": false, "lockedStatus": false, "title": "StatTrak\u2122 M4A1-S | Basilisk (Factory New)", "status": "active", "dm_discount": 22, "dm_price": {"value": 23.62, "currency": "USD", "cValue": null, "cCurrency": null}, "sm_price": null, "steam_name_id": "23853302", "histogram": null}, {"itemId": "188530139:937348442:27848636090:730", "amount": 1, "inMarket": false, "lockedStatus": false, "title": "M4A1-S | Hyper Beast (Well-Worn)", "status": "active", "dm_discount": 21, "dm_price": {"value": 12.3, "currency": "USD", "cValue": null, "cCurrency": null}, "sm_price": null, "steam_name_id": "40097839", "histogram": null}, {"itemId": "188530139:2961402211:27860929174:730", "amount": 1, "inMarket": false, "lockedStatus": false, "title": "M4A1-S | Nightmare (Minimal Wear)", "status": "active", "dm_discount": 21, "dm_price": {"value": 14.8, "currency": "USD", "cValue": null, "cCurrency": null}, "sm_price": null, "steam_name_id": "175999903", "histogram": null}, {"itemId": "902658099:2533347999:27846086624:730", "amount": 1, "inMarket": false, "lockedStatus": false, "title": "StatTrak\u2122 M4A1-S | Leaded Glass (Minimal Wear)", "status": "active", "dm_discount": 21, "dm_price": {"value": 12.01, "currency": "USD", "cValue": null, "cCurrency": null}, "sm_price": null, "steam_name_id": "175917399", "histogram": null}, {"itemId": "480085569:1704739900:27846448703:730", "amount": 1, "inMarket": false, "lockedStatus": false, "title": "M4A1-S | Chantico's Fire (Well-Worn)", "status": "active", "dm_discount": 21, "dm_price": {"value": 13.82, "currency": "USD", "cValue": null, "cCurrency": null}, "sm_price": null, "steam_name_id": "149872485", "histogram": null}, {"itemId": "188530139:2962906629:27856925229:730", "amount": 1, "inMarket": false, "lockedStatus": false, "title": "\u2605 Navaja Knife | Crimson Web (Field-Tested)", "status": "active", "dm_discount": 20, "dm_price": {"value": 65.02, "currency": "USD", "cValue": null, "cCurrency": null}, "sm_price": null, "steam_name_id": "176000128", "histogram": null}, {"itemId": "188530139:4842644741:27845961019:730", "amount": 1, "inMarket": false, "lockedStatus": false, "title": "M4A1-S | Decimator (Field-Tested)", "status": "active", "dm_discount": 20, "dm_price": {"value": 8.47, "currency": "USD", "cValue": null, "cCurrency": null}, "sm_price": null, "steam_name_id": "175880299", "histogram": null}, {"itemId": "188530139:2251347058:27846740917:730", "amount": 1, "inMarket": false, "lockedStatus": false, "title": "M4A1-S | Decimator (Field-Tested)", "status": "active", "dm_discount": 19, "dm_price": {"value": 8.49, "currency": "USD", "cValue": null, "cCurrency": null}, "sm_price": null, "steam_name_id": "175880299", "histogram": null}, {"itemId": "480085569:2532028335:27845268837:730", "amount": 1, "inMarket": false, "lockedStatus": false, "title": "M4A1-S | Leaded Glass (Factory New)", "status": "active", "dm_discount": 19, "dm_price": {"value": 8.72, "currency": "USD", "cValue": null, "cCurrency": null}, "sm_price": null, "steam_name_id": "175917369", "histogram": null}, {"itemId": "188530139:3924144555:27847978165:730", "amount": 1, "inMarket": false, "lockedStatus": false, "title": "AK-47 | Frontside Misty (Field-Tested)", "status": "active", "dm_discount": 19, "dm_price": {"value": 10.25, "currency": "USD", "cValue": null, "cCurrency": null}, "sm_price": null, "steam_name_id": "67060996", "histogram": null}, {"itemId": "188530139:5098038709:27867162261:730", "amount": 1, "inMarket": false, "lockedStatus": false, "title": "AUG | Death by Puppy (Factory New)", "status": "active", "dm_discount": 19, "dm_price": {"value": 7.82, "currency": "USD", "cValue": null, "cCurrency": null}, "sm_price": null, "steam_name_id": "176091863", "histogram": null}, {"itemId": "188530139:1309998165:27866319418:730", "amount": 1, "inMarket": false, "lockedStatus": false, "title": "AK-47 | Frontside Misty (Field-Tested)", "status": "active", "dm_discount": 19, "dm_price": {"value": 10.26, "currency": "USD", "cValue": null, "cCurrency": null}, "sm_price": null, "steam_name_id": "67060996", "histogram": null}, {"itemId": "188530139:1309998165:27857012342:730", "amount": 1, "inMarket": false, "lockedStatus": false, "title": "AK-47 | Frontside Misty (Field-Tested)", "status": "active", "dm_discount": 19, "dm_price": {"value": 10.26, "currency": "USD", "cValue": null, "cCurrency": null}, "sm_price": null, "steam_name_id": "67060996", "histogram": null}, {"itemId": "188530139:1309998165:27853726062:730", "amount": 1, "inMarket": false, "lockedStatus": false, "title": "AK-47 | Frontside Misty (Field-Tested)", "status": "active", "dm_discount": 19, "dm_price": {"value": 10.26, "currency": "USD", "cValue": null, "cCurrency": null}, "sm_price": null, "steam_name_id": "67060996", "histogram": null}, {"itemId": "480085569:4839718519:27853453664:730", "amount": 1, "inMarket": false, "lockedStatus": false, "title": "AK-47 | Frontside Misty (Field-Tested)", "status": "active", "dm_discount": 19, "dm_price": {"value": 10.26, "currency": "USD", "cValue": null, "cCurrency": null}, "sm_price": null, "steam_name_id": "67060996", "histogram": null}, {"itemId": "188530139:4911431931:27851726819:730", "amount": 1, "inMarket": false, "lockedStatus": false, "title": "M4A1-S | Decimator (Well-Worn)", "status": "active", "dm_discount": 19, "dm_price": {"value": 9.6, "currency": "USD", "cValue": null, "cCurrency": null}, "sm_price": null, "steam_name_id": "175880409", "histogram": null}, {"itemId": "188530139:2532028335:27855462862:730", "amount": 1, "inMarket": false, "lockedStatus": false, "title": "M4A1-S | Leaded Glass (Factory New)", "status": "active", "dm_discount": 19, "dm_price": {"value": 8.74, "currency": "USD", "cValue": null, "cCurrency": null}, "sm_price": null, "steam_name_id": "175917369", "histogram": null}, {"itemId": "902658099:4800253430:27850804834:730", "amount": 1, "inMarket": false, "lockedStatus": false, "title": "StatTrak\u2122 MP7 | Neon Ply (Factory New)", "status": "active", "dm_discount": 19, "dm_price": {"value": 8.19, "currency": "USD", "cValue": null, "cCurrency": null}, "sm_price": null, "steam_name_id": "176096900", "histogram": null}, {"itemId": "480085569:2532028335:27864929942:730", "amount": 1, "inMarket": false, "lockedStatus": false, "title": "M4A1-S | Leaded Glass (Factory New)", "status": "active", "dm_discount": 19, "dm_price": {"value": 8.75, "currency": "USD", "cValue": null, "cCurrency": null}, "sm_price": null, "steam_name_id": "175917369", "histogram": null}, {"itemId": "188530139:5098265341:27862236391:730", "amount": 1, "inMarket": false, "lockedStatus": false, "title": "M4A1-S | Decimator (Factory New)", "status": "active", "dm_discount": 19, "dm_price": {"value": 20.48, "currency": "USD", "cValue": null, "cCurrency": null}, "sm_price": null, "steam_name_id": "175880338", "histogram": null}, {"itemId": "480085569:4646750607:27854521295:730", "amount": 1, "inMarket": false, "lockedStatus": false, "title": "M4A1-S | Decimator (Field-Tested)", "status": "active", "dm_discount": 19, "dm_price": {"value": 8.53, "currency": "USD", "cValue": null, "cCurrency": null}, "sm_price": null, "steam_name_id": "175880299", "histogram": null}, {"itemId": "188530139:2220009215:27850246603:730", "amount": 1, "inMarket": false, "lockedStatus": false, "title": "M4A1-S | Decimator (Field-Tested)", "status": "active", "dm_discount": 19, "dm_price": {"value": 8.53, "currency": "USD", "cValue": null, "cCurrency": null}, "sm_price": null, "steam_name_id": "175880299", "histogram": null}, {"itemId": "188530139:2220009215:27853164939:730", "amount": 1, "inMarket": false, "lockedStatus": false, "title": "M4A1-S | Decimator (Field-Tested)", "status": "active", "dm_discount": 19, "dm_price": {"value": 8.53, "currency": "USD", "cValue": null, "cCurrency": null}, "sm_price": null, "steam_name_id": "175880299", "histogram": null}, {"itemId": "480085569:5098940544:27868659011:730", "amount": 1, "inMarket": false, "lockedStatus": false, "title": "M4A1-S | Decimator (Field-Tested)", "status": "active", "dm_discount": 19, "dm_price": {"value": 8.57, "currency": "USD", "cValue": null, "cCurrency": null}, "sm_price": null, "steam_name_id": "175880299", "histogram": null}, {"itemId": "188530139:5098019033:27864004705:730", "amount": 1, "inMarket": false, "lockedStatus": false, "title": "AK-47 | Ice Coaled (Field-Tested)", "status": "active", "dm_discount": 19, "dm_price": {"value": 13.46, "currency": "USD", "cValue": null, "cCurrency": null}, "sm_price": null, "steam_name_id": "176321254", "histogram": null}, {"itemId": "188530139:3609230556:27859474064:730", "amount": 1, "inMarket": false, "lockedStatus": false, "title": "M4A1-S | Decimator (Well-Worn)", "status": "active", "dm_discount": 18, "dm_price": {"value": 9.68, "currency": "USD", "cValue": null, "cCurrency": null}, "sm_price": null, "steam_name_id": "175880409", "histogram": null}, {"itemId": "480085569:4982352612:27854952824:730", "amount": 1, "inMarket": false, "lockedStatus": false, "title": "M4A1-S | Hyper Beast (Field-Tested)", "status": "active", "dm_discount": 18, "dm_price": {"value": 17.22, "currency": "USD", "cValue": null, "cCurrency": null}, "sm_price": null, "steam_name_id": "40097840", "histogram": null}, {"itemId": "188530139:1816238255:27848286413:730", "amount": 1, "inMarket": false, "lockedStatus": false, "title": "\u2605 Gut Knife | Freehand (Minimal Wear)", "status": "active", "dm_discount": 18, "dm_price": {"value": 71.12, "currency": "USD", "cValue": null, "cCurrency": null}, "sm_price": null, "steam_name_id": "156239389", "histogram": null}, {"itemId": "188530139:2220018982:27854315257:730", "amount": 1, "inMarket": false, "lockedStatus": false, "title": "CZ75-Auto | Xiangliu (Factory New)", "status": "active", "dm_discount": 18, "dm_price": {"value": 7.35, "currency": "USD", "cValue": null, "cCurrency": null}, "sm_price": null, "steam_name_id": "175880287", "histogram": null}, {"itemId": "188530139:520033301:27859474093:730", "amount": 1, "inMarket": false, "lockedStatus": false, "title": "P90 | Asiimov (Well-Worn)", "status": "active", "dm_discount": 18, "dm_price": {"value": 5.05, "currency": "USD", "cValue": null, "cCurrency": null}, "sm_price": null, "steam_name_id": "14963002", "histogram": null}, {"itemId": "188530170:3232186512:27845048249:730", "amount": 1, "inMarket": false, "lockedStatus": false, "title": "\u2605 StatTrak\u2122 Navaja Knife | Ultraviolet (Field-Tested)", "status": "active", "dm_discount": 18, "dm_price": {"value": 61.0, "currency": "USD", "cValue": null, "cCurrency": null}, "sm_price": null, "steam_name_id": "176043384", "histogram": null}, {"itemId": "188530139:2940582982:27845095864:730", "amount": 1, "inMarket": false, "lockedStatus": false, "title": "M4A1-S | Mecha Industries (Field-Tested)", "status": "active", "dm_discount": 18, "dm_price": {"value": 19.42, "currency": "USD", "cValue": null, "cCurrency": null}, "sm_price": null, "steam_name_id": "156113447", "histogram": null}, {"itemId": "188530170:5098138931:27867457265:730", "amount": 1, "inMarket": false, "lockedStatus": false, "title": "StatTrak\u2122 M4A1-S | Nightmare (Minimal Wear)", "status": "active", "dm_discount": 18, "dm_price": {"value": 33.89, "currency": "USD", "cValue": null, "cCurrency": null}, "sm_price": null, "steam_name_id": "176000100", "histogram": null}, {"itemId": "188530170:4461922416:27853524568:730", "amount": 1, "inMarket": false, "lockedStatus": false, "title": "StatTrak\u2122 M4A1-S | Nightmare (Minimal Wear)", "status": "active", "dm_discount": 18, "dm_price": {"value": 33.89, "currency": "USD", "cValue": null, "cCurrency": null}, "sm_price": null, "steam_name_id": "176000100", "histogram": null}, {"itemId": "188530170:5098543248:27865617441:730", "amount": 1, "inMarket": false, "lockedStatus": false, "title": "StatTrak\u2122 Desert Eagle | Mecha Industries (Minimal Wear)", "status": "active", "dm_discount": 18, "dm_price": {"value": 10.03, "currency": "USD", "cValue": null, "cCurrency": null}, "sm_price": null, "steam_name_id": "176024925", "histogram": null}, {"itemId": "188530139:2960971233:27850873630:730", "amount": 1, "inMarket": false, "lockedStatus": false, "title": "M4A1-S | Nightmare (Field-Tested)", "status": "active", "dm_discount": 18, "dm_price": {"value": 8.37, "currency": "USD", "cValue": null, "cCurrency": null}, "sm_price": null, "steam_name_id": "175999966", "histogram": null}, {"itemId": "480085569:5038257434:27513755653:730", "amount": 1, "inMarket": false, "lockedStatus": false, "title": "M4A1-S | Nitro (Factory New)", "status": "active", "dm_discount": 18, "dm_price": {"value": 6.53, "currency": "USD", "cValue": null, "cCurrency": null}, "sm_price": null, "steam_name_id": "2392466", "histogram": null}, {"itemId": "480085569:4629089541:27854960621:730", "amount": 1, "inMarket": false, "lockedStatus": false, "title": "M4A1-S | Mecha Industries (Field-Tested)", "status": "active", "dm_discount": 18, "dm_price": {"value": 19.5, "currency": "USD", "cValue": null, "cCurrency": null}, "sm_price": null, "steam_name_id": "156113447", "histogram": null}, {"itemId": "480085569:2960971233:27859474116:730", "amount": 1, "inMarket": false, "lockedStatus": false, "title": "M4A1-S | Nightmare (Field-Tested)", "status": "active", "dm_discount": 18, "dm_price": {"value": 8.38, "currency": "USD", "cValue": null, "cCurrency": null}, "sm_price": null, "steam_name_id": "175999966", "histogram": null}, {"itemId": "480085569:2960971233:27855129344:730", "amount": 1, "inMarket": false, "lockedStatus": false, "title": "M4A1-S | Nightmare (Field-Tested)", "status": "active", "dm_discount": 18, "dm_price": {"value": 8.38, "currency": "USD", "cValue": null, "cCurrency": null}, "sm_price": null, "steam_name_id": "175999966", "histogram": null}, {"itemId": "480085569:4642813342:27848203150:730", "amount": 1, "inMarket": false, "lockedStatus": false, "title": "AK-47 | Baroque Purple (Factory New)", "status": "active", "dm_discount": 18, "dm_price": {"value": 7.95, "currency": "USD", "cValue": null, "cCurrency": null}, "sm_price": null, "steam_name_id": "176096831", "histogram": null}, {"itemId": "188530139:4991739938:27864705472:730", "amount": 1, "inMarket": false, "lockedStatus": false, "title": "M4A4 | Bullet Rain (Minimal Wear)", "status": "active", "dm_discount": 18, "dm_price": {"value": 17.98, "currency": "USD", "cValue": null, "cCurrency": null}, "sm_price": null, "steam_name_id": "15492615", "histogram": null}, {"itemId": "188530139:937306045:27859474065:730", "amount": 1, "inMarket": false, "lockedStatus": false, "title": "M4A1-S | Hyper Beast (Field-Tested)", "status": "active", "dm_discount": 18, "dm_price": {"value": 17.4, "currency": "USD", "cValue": null, "cCurrency": null}, "sm_price": null, "steam_name_id": "40097840", "histogram": null}, {"itemId": "188530139:1812832980:27859474076:730", "amount": 1, "inMarket": false, "lockedStatus": false, "title": "M4A1-S | Mecha Industries (Field-Tested)", "status": "active", "dm_discount": 17, "dm_price": {"value": 19.54, "currency": "USD", "cValue": null, "cCurrency": null}, "sm_price": null, "steam_name_id": "156113447", "histogram": null}, {"itemId": "480085569:3770669123:27845017972:730", "amount": 1, "inMarket": false, "lockedStatus": false, "title": "M4A1-S | Player Two (Field-Tested)", "status": "active", "dm_discount": 17, "dm_price": {"value": 20.91, "currency": "USD", "cValue": null, "cCurrency": null}, "sm_price": null, "steam_name_id": "176118368", "histogram": null}, {"itemId": "188530170:4675929574:25225285995:730", "amount": 1, "inMarket": false, "lockedStatus": false, "title": "StatTrak\u2122 AK-47 | Rat Rod (Minimal Wear)", "status": "active", "dm_discount": 17, "dm_price": {"value": 8.99, "currency": "USD", "cValue": null, "cCurrency": null}, "sm_price": null, "steam_name_id": "176096548", "histogram": null}, {"itemId": "902658099:4976608854:27848257697:730", "amount": 1, "inMarket": false, "lockedStatus": false, "title": "StatTrak\u2122 AK-47 | Nightwish (Field-Tested)", "status": "active", "dm_discount": 17, "dm_price": {"value": 40.76, "currency": "USD", "cValue": null, "cCurrency": null}, "sm_price": null, "steam_name_id": "176288663", "histogram": null}, {"itemId": "188530170:5033874457:27848507670:730", "amount": 1, "inMarket": false, "lockedStatus": false, "title": "StatTrak\u2122 USP-S | Cortex (Minimal Wear)", "status": "active", "dm_discount": 17, "dm_price": {"value": 7.04, "currency": "USD", "cValue": null, "cCurrency": null}, "sm_price": null, "steam_name_id": "175966926", "histogram": null}, {"itemId": "188530170:1441632782:27868315369:730", "amount": 1, "inMarket": false, "lockedStatus": false, "title": "StatTrak\u2122 AK-47 | Point Disarray (Minimal Wear)", "status": "active", "dm_discount": 17, "dm_price": {"value": 30.87, "currency": "USD", "cValue": null, "cCurrency": null}, "sm_price": null, "steam_name_id": "84474903", "histogram": null}, {"itemId": "188530139:5049984365:27849517549:730", "amount": 1, "inMarket": false, "lockedStatus": false, "title": "AK-47 | Nightwish (Well-Worn)", "status": "active", "dm_discount": 17, "dm_price": {"value": 14.08, "currency": "USD", "cValue": null, "cCurrency": null}, "sm_price": null, "steam_name_id": "176288618", "histogram": null}, {"itemId": "188530139:2960971233:27863602398:730", "amount": 1, "inMarket": false, "lockedStatus": false, "title": "M4A1-S | Nightmare (Field-Tested)", "status": "active", "dm_discount": 17, "dm_price": {"value": 8.43, "currency": "USD", "cValue": null, "cCurrency": null}, "sm_price": null, "steam_name_id": "175999966", "histogram": null}, {"itemId": "188530139:2961434301:27852350790:730", "amount": 1, "inMarket": false, "lockedStatus": false, "title": "M4A1-S | Nightmare (Well-Worn)", "status": "active", "dm_discount": 17, "dm_price": {"value": 6.28, "currency": "USD", "cValue": null, "cCurrency": null}, "sm_price": null, "steam_name_id": "175999991", "histogram": null}, {"itemId": "480085569:4578727895:27850683739:730", "amount": 1, "inMarket": false, "lockedStatus": false, "title": "AK-47 | Green Laminate (Factory New)", "status": "active", "dm_discount": 17, "dm_price": {"value": 8.22, "currency": "USD", "cValue": null, "cCurrency": null}, "sm_price": null, "steam_name_id": "176262729", "histogram": null}, {"itemId": "480085569:4614826480:27848203134:730", "amount": 1, "inMarket": false, "lockedStatus": false, "title": "AK-47 | Green Laminate (Factory New)", "status": "active", "dm_discount": 17, "dm_price": {"value": 8.22, "currency": "USD", "cValue": null, "cCurrency": null}, "sm_price": null, "steam_name_id": "176262729", "histogram": null}, {"itemId": "188530170:5098053046:27862113562:730", "amount": 1, "inMarket": false, "lockedStatus": false, "title": "StatTrak\u2122 Desert Eagle | Conspiracy (Minimal Wear)", "status": "active", "dm_discount": 17, "dm_price": {"value": 11.33, "currency": "USD", "cValue": null, "cCurrency": null}, "sm_price": null, "steam_name_id": "14966464", "histogram": null}, {"itemId": "188530139:4911008593:27858444192:730", "amount": 1, "inMarket": false, "lockedStatus": false, "title": "AK-47 | The Empress (Well-Worn)", "status": "active", "dm_discount": 17, "dm_price": {"value": 16.13, "currency": "USD", "cValue": null, "cCurrency": null}, "sm_price": null, "steam_name_id": "175917420", "histogram": null}, {"itemId": "188530139:4428767811:27856246908:730", "amount": 1, "inMarket": false, "lockedStatus": false, "title": "USP-S | The Traitor (Battle-Scarred)", "status": "active", "dm_discount": 17, "dm_price": {"value": 8.15, "currency": "USD", "cValue": null, "cCurrency": null}, "sm_price": null, "steam_name_id": "176241084", "histogram": null}, {"itemId": "188530139:5069912561:27859508577:730", "amount": 1, "inMarket": false, "lockedStatus": false, "title": "USP-S | The Traitor (Battle-Scarred)", "status": "active", "dm_discount": 17, "dm_price": {"value": 8.15, "currency": "USD", "cValue": null, "cCurrency": null}, "sm_price": null, "steam_name_id": "176241084", "histogram": null}, {"itemId": "188530139:5108200233:27862539611:730", "amount": 1, "inMarket": false, "lockedStatus": false, "title": "M4A1-S | Mecha Industries (Field-Tested)", "status": "active", "dm_discount": 17, "dm_price": {"value": 19.66, "currency": "USD", "cValue": null, "cCurrency": null}, "sm_price": null, "steam_name_id": "156113447", "histogram": null}, {"itemId": "902658099:5011105804:27850683798:730", "amount": 1, "inMarket": false, "lockedStatus": false, "title": "StatTrak\u2122 MP9 | Food Chain (Factory New)", "status": "active", "dm_discount": 17, "dm_price": {"value": 18.12, "currency": "USD", "cValue": null, "cCurrency": null}, "sm_price": null, "steam_name_id": "176241065", "histogram": null}, {"itemId": "188530139:3770669123:27846745034:730", "amount": 1, "inMarket": false, "lockedStatus": false, "title": "M4A1-S | Player Two (Field-Tested)", "status": "active", "dm_discount": 17, "dm_price": {"value": 21.03, "currency": "USD", "cValue": null, "cCurrency": null}, "sm_price": null, "steam_name_id": "176118368", "histogram": null}, {"itemId": "188530170:4616546182:27852401077:730", "amount": 1, "inMarket": false, "lockedStatus": false, "title": "StatTrak\u2122 AK-47 | Slate (Battle-Scarred)", "status": "active", "dm_discount": 17, "dm_price": {"value": 6.78, "currency": "USD", "cValue": null, "cCurrency": null}, "sm_price": null, "steam_name_id": "176241094", "histogram": null}, {"itemId": "188530139:2237826187:22235265053:730", "amount": 1, "inMarket": false, "lockedStatus": false, "title": "\u2605 Falchion Knife | Damascus Steel (Battle-Scarred)", "status": "active", "dm_discount": 17, "dm_price": {"value": 90.88, "currency": "USD", "cValue": null, "cCurrency": null}, "sm_price": null, "steam_name_id": "175881996", "histogram": null}, {"itemId": "188530139:4141785092:27861199576:730", "amount": 1, "inMarket": false, "lockedStatus": false, "title": "USP-S | Monster Mashup (Factory New)", "status": "active", "dm_discount": 17, "dm_price": {"value": 24.62, "currency": "USD", "cValue": null, "cCurrency": null}, "sm_price": null, "steam_name_id": "176209198", "histogram": null}, {"itemId": "188530170:1440626702:27857585857:730", "amount": 1, "inMarket": false, "lockedStatus": false, "title": "StatTrak\u2122 AK-47 | Point Disarray (Field-Tested)", "status": "active", "dm_discount": 17, "dm_price": {"value": 18.64, "currency": "USD", "cValue": null, "cCurrency": null}, "sm_price": null, "steam_name_id": "84444492", "histogram": null}, {"itemId": "188530139:3955310082:27867826453:730", "amount": 1, "inMarket": false, "lockedStatus": false, "title": "AK-47 | Legion of Anubis (Field-Tested)", "status": "active", "dm_discount": 17, "dm_price": {"value": 8.6, "currency": "USD", "cValue": null, "cCurrency": null}, "sm_price": null, "steam_name_id": "176185973", "histogram": null}, {"itemId": "188530170:5077583841:27859532750:730", "amount": 1, "inMarket": false, "lockedStatus": false, "title": "StatTrak\u2122 AK-47 | Slate (Well-Worn)", "status": "active", "dm_discount": 17, "dm_price": {"value": 6.79, "currency": "USD", "cValue": null, "cCurrency": null}, "sm_price": null, "steam_name_id": "176240976", "histogram": null}, {"itemId": "188530170:2220090827:27854605200:730", "amount": 1, "inMarket": false, "lockedStatus": false, "title": "StatTrak\u2122 M4A1-S | Decimator (Field-Tested)", "status": "active", "dm_discount": 17, "dm_price": {"value": 17.52, "currency": "USD", "cValue": null, "cCurrency": null}, "sm_price": null, "steam_name_id": "175880362", "histogram": null}, {"itemId": "188530170:4927539643:27853557267:730", "amount": 1, "inMarket": false, "lockedStatus": false, "title": "StatTrak\u2122 M4A1-S | Decimator (Field-Tested)", "status": "active", "dm_discount": 17, "dm_price": {"value": 17.52, "currency": "USD", "cValue": null, "cCurrency": null}, "sm_price": null, "steam_name_id": "175880362", "histogram": null}, {"itemId": "188530170:2220090827:27848507749:730", "amount": 1, "inMarket": false, "lockedStatus": false, "title": "StatTrak\u2122 M4A1-S | Decimator (Field-Tested)", "status": "active", "dm_discount": 17, "dm_price": {"value": 17.52, "currency": "USD", "cValue": null, "cCurrency": null}, "sm_price": null, "steam_name_id": "175880362", "histogram": null}, {"itemId": "188530139:1934517468:27849250119:730", "amount": 1, "inMarket": false, "lockedStatus": false, "title": "AK-47 | Neon Revolution (Field-Tested)", "status": "active", "dm_discount": 17, "dm_price": {"value": 12.4, "currency": "USD", "cValue": null, "cCurrency": null}, "sm_price": null, "steam_name_id": "165031020", "histogram": null}, {"itemId": "188530139:1934517468:27848636069:730", "amount": 1, "inMarket": false, "lockedStatus": false, "title": "AK-47 | Neon Revolution (Field-Tested)", "status": "active", "dm_discount": 17, "dm_price": {"value": 12.4, "currency": "USD", "cValue": null, "cCurrency": null}, "sm_price": null, "steam_name_id": "165031020", "histogram": null}, {"itemId": "188530139:3221924964:27854499229:730", "amount": 1, "inMarket": false, "lockedStatus": false, "title": "\u2605 Navaja Knife | Rust Coat (Battle-Scarred)", "status": "active", "dm_discount": 17, "dm_price": {"value": 49.65, "currency": "USD", "cValue": null, "cCurrency": null}, "sm_price": null, "steam_name_id": "176042730", "histogram": null}, {"itemId": "188530139:5005894032:27850654761:730", "amount": 1, "inMarket": false, "lockedStatus": false, "title": "USP-S | The Traitor (Well-Worn)", "status": "active", "dm_discount": 17, "dm_price": {"value": 9.08, "currency": "USD", "cValue": null, "cCurrency": null}, "sm_price": null, "steam_name_id": "176241049", "histogram": null}, {"itemId": "188530139:310776829:27867921158:730", "amount": 1, "inMarket": false, "lockedStatus": false, "title": "Galil AR | Orange DDPAT (Field-Tested)", "status": "active", "dm_discount": 17, "dm_price": {"value": 8.12, "currency": "USD", "cValue": null, "cCurrency": null}, "sm_price": null, "steam_name_id": "1321383", "histogram": null}, {"itemId": "480085569:3770686763:27866446959:730", "amount": 1, "inMarket": false, "lockedStatus": false, "title": "Glock-18 | Bullet Queen (Field-Tested)", "status": "active", "dm_discount": 17, "dm_price": {"value": 7.25, "currency": "USD", "cValue": null, "cCurrency": null}, "sm_price": null, "steam_name_id": "176118407", "histogram": null}, {"itemId": "480085569:4363194681:27848682517:730", "amount": 1, "inMarket": false, "lockedStatus": false, "title": "AK-47 | Phantom Disruptor (Well-Worn)", "status": "active", "dm_discount": 17, "dm_price": {"value": 5.17, "currency": "USD", "cValue": null, "cCurrency": null}, "sm_price": null, "steam_name_id": "176118433", "histogram": null}, {"itemId": "188530139:4310713295:27859592564:730", "amount": 1, "inMarket": false, "lockedStatus": false, "title": "M4A1-S | Nightmare (Battle-Scarred)", "status": "active", "dm_discount": 17, "dm_price": {"value": 5.81, "currency": "USD", "cValue": null, "cCurrency": null}, "sm_price": null, "steam_name_id": "176000021", "histogram": null}, {"itemId": "188530139:5073028707:27858936068:730", "amount": 1, "inMarket": false, "lockedStatus": false, "title": "AK-47 | Neon Revolution (Field-Tested)", "status": "active", "dm_discount": 17, "dm_price": {"value": 12.43, "currency": "USD", "cValue": null, "cCurrency": null}, "sm_price": null, "steam_name_id": "165031020", "histogram": null}, {"itemId": "188530139:2961434301:27851802407:730", "amount": 1, "inMarket": false, "lockedStatus": false, "title": "M4A1-S | Nightmare (Well-Worn)", "status": "active", "dm_discount": 17, "dm_price": {"value": 6.32, "currency": "USD", "cValue": null, "cCurrency": null}, "sm_price": null, "steam_name_id": "175999991", "histogram": null}, {"itemId": "188530139:4640538552:27859513316:730", "amount": 1, "inMarket": false, "lockedStatus": false, "title": "AK-47 | The Empress (Well-Worn)", "status": "active", "dm_discount": 17, "dm_price": {"value": 16.23, "currency": "USD", "cValue": null, "cCurrency": null}, "sm_price": null, "steam_name_id": "175917420", "histogram": null}, {"itemId": "188530139:5098027047:27866934104:730", "amount": 1, "inMarket": false, "lockedStatus": false, "title": "Sawed-Off | Kiss\u2665Love (Field-Tested)", "status": "active", "dm_discount": 17, "dm_price": {"value": 5.81, "currency": "USD", "cValue": null, "cCurrency": null}, "sm_price": null, "steam_name_id": "176321281", "histogram": null}, {"itemId": "188530415:3957267804:27850240555:730", "amount": 1, "inMarket": false, "lockedStatus": false, "title": "StatTrak\u2122 M4A4 | Tooth Fairy (Well-Worn)", "status": "active", "dm_discount": 16, "dm_price": {"value": 5.0, "currency": "USD", "cValue": null, "cCurrency": null}, "sm_price": null, "steam_name_id": "176186199", "histogram": null}, {"itemId": "188530139:4428828851:27859734099:730", "amount": 1, "inMarket": false, "lockedStatus": false, "title": "USP-S | The Traitor (Well-Worn)", "status": "active", "dm_discount": 16, "dm_price": {"value": 9.11, "currency": "USD", "cValue": null, "cCurrency": null}, "sm_price": null, "steam_name_id": "176241049", "histogram": null}, {"itemId": "480085569:3770670561:27849187376:730", "amount": 1, "inMarket": false, "lockedStatus": false, "title": "AK-47 | Phantom Disruptor (Minimal Wear)", "status": "active", "dm_discount": 16, "dm_price": {"value": 6.22, "currency": "USD", "cValue": null, "cCurrency": null}, "sm_price": null, "steam_name_id": "176118310", "histogram": null}, {"itemId": "188530139:5015516417:27848152783:730", "amount": 1, "inMarket": false, "lockedStatus": false, "title": "M4A1-S | Cyrex (Factory New)", "status": "active", "dm_discount": 16, "dm_price": {"value": 23.94, "currency": "USD", "cValue": null, "cCurrency": null}, "sm_price": null, "steam_name_id": "14962984", "histogram": null}, {"itemId": "188530139:2961573476:27861301352:730", "amount": 1, "inMarket": false, "lockedStatus": false, "title": "M4A1-S | Nightmare (Battle-Scarred)", "status": "active", "dm_discount": 16, "dm_price": {"value": 5.83, "currency": "USD", "cValue": null, "cCurrency": null}, "sm_price": null, "steam_name_id": "176000021", "histogram": null}, {"itemId": "188530170:1935196075:27857030151:730", "amount": 1, "inMarket": false, "lockedStatus": false, "title": "StatTrak\u2122 Tec-9 | Fuel Injector (Factory New)", "status": "active", "dm_discount": 16, "dm_price": {"value": 24.16, "currency": "USD", "cValue": null, "cCurrency": null}, "sm_price": null, "steam_name_id": "165100544", "histogram": null}, {"itemId": "480085569:4303553323:27868160725:730", "amount": 1, "inMarket": false, "lockedStatus": false, "title": "MP9 | Hydra (Minimal Wear)", "status": "active", "dm_discount": 16, "dm_price": {"value": 5.18, "currency": "USD", "cValue": null, "cCurrency": null}, "sm_price": null, "steam_name_id": "176091864", "histogram": null}, {"itemId": "188530139:3275200469:27854820046:730", "amount": 1, "inMarket": false, "lockedStatus": false, "title": "M4A1-S | Cyrex (Field-Tested)", "status": "active", "dm_discount": 16, "dm_price": {"value": 12.41, "currency": "USD", "cValue": null, "cCurrency": null}, "sm_price": null, "steam_name_id": "14962989", "histogram": null}, {"itemId": "188530139:3770670561:27857856595:730", "amount": 1, "inMarket": false, "lockedStatus": false, "title": "AK-47 | Phantom Disruptor (Minimal Wear)", "status": "active", "dm_discount": 16, "dm_price": {"value": 6.23, "currency": "USD", "cValue": null, "cCurrency": null}, "sm_price": null, "steam_name_id": "176118310", "histogram": null}, {"itemId": "188530139:5098020417:27869264868:730", "amount": 1, "inMarket": false, "lockedStatus": false, "title": "M4A1-S | Nightmare (Field-Tested)", "status": "active", "dm_discount": 16, "dm_price": {"value": 8.52, "currency": "USD", "cValue": null, "cCurrency": null}, "sm_price": null, "steam_name_id": "175999966", "histogram": null}, {"itemId": "480085569:4896850646:27866907396:730", "amount": 1, "inMarket": false, "lockedStatus": false, "title": "M4A1-S | Nightmare (Field-Tested)", "status": "active", "dm_discount": 16, "dm_price": {"value": 8.52, "currency": "USD", "cValue": null, "cCurrency": null}, "sm_price": null, "steam_name_id": "175999966", "histogram": null}, {"itemId": "188530139:1934965583:27845562519:730", "amount": 1, "inMarket": false, "lockedStatus": false, "title": "AUG | Syd Mead (Factory New)", "status": "active", "dm_discount": 16, "dm_price": {"value": 5.59, "currency": "USD", "cValue": null, "cCurrency": null}, "sm_price": null, "steam_name_id": "165036844", "histogram": null}, {"itemId": "188530139:2578896192:27867457239:730", "amount": 1, "inMarket": false, "lockedStatus": false, "title": "AK-47 | The Empress (Field-Tested)", "status": "active", "dm_discount": 16, "dm_price": {"value": 19.82, "currency": "USD", "cValue": null, "cCurrency": null}, "sm_price": null, "steam_name_id": "175917356", "histogram": null}, {"itemId": "188530139:4910475845:27865593701:730", "amount": 1, "inMarket": false, "lockedStatus": false, "title": "AK-47 | Ice Coaled (Minimal Wear)", "status": "active", "dm_discount": 16, "dm_price": {"value": 25.67, "currency": "USD", "cValue": null, "cCurrency": null}, "sm_price": null, "steam_name_id": "176321169", "histogram": null}, {"itemId": "188530139:1934517468:27859474067:730", "amount": 1, "inMarket": false, "lockedStatus": false, "title": "AK-47 | Neon Revolution (Field-Tested)", "status": "active", "dm_discount": 16, "dm_price": {"value": 12.52, "currency": "USD", "cValue": null, "cCurrency": null}, "sm_price": null, "steam_name_id": "165031020", "histogram": null}, {"itemId": "188530170:1563143102:27110546551:730", "amount": 1, "inMarket": false, "lockedStatus": false, "title": "\u2605 StatTrak\u2122 Bowie Knife | Urban Masked (Field-Tested)", "status": "active", "dm_discount": 16, "dm_price": {"value": 90.29, "currency": "USD", "cValue": null, "cCurrency": null}, "sm_price": null, "steam_name_id": "139854428", "histogram": null}, {"itemId": "902658099:4851518731:27857030157:730", "amount": 1, "inMarket": false, "lockedStatus": false, "title": "StatTrak\u2122 USP-S | The Traitor (Field-Tested)", "status": "active", "dm_discount": 16, "dm_price": {"value": 30.7, "currency": "USD", "cValue": null, "cCurrency": null}, "sm_price": null, "steam_name_id": "176241121", "histogram": null}, {"itemId": "188530139:5098018820:27864688863:730", "amount": 1, "inMarket": false, "lockedStatus": false, "title": "M4A1-S | Player Two (Field-Tested)", "status": "active", "dm_discount": 16, "dm_price": {"value": 21.28, "currency": "USD", "cValue": null, "cCurrency": null}, "sm_price": null, "steam_name_id": "176118368", "histogram": null}, {"itemId": "188530139:1934965583:27846461839:730", "amount": 1, "inMarket": false, "lockedStatus": false, "title": "AUG | Syd Mead (Factory New)", "status": "active", "dm_discount": 16, "dm_price": {"value": 5.61, "currency": "USD", "cValue": null, "cCurrency": null}, "sm_price": null, "steam_name_id": "165036844", "histogram": null}, {"itemId": "188530139:5098028576:27868245631:730", "amount": 1, "inMarket": false, "lockedStatus": false, "title": "M4A1-S | Cyrex (Field-Tested)", "status": "active", "dm_discount": 16, "dm_price": {"value": 12.46, "currency": "USD", "cValue": null, "cCurrency": null}, "sm_price": null, "steam_name_id": "14962989", "histogram": null}, {"itemId": "480085569:4665273492:27848203157:730", "amount": 1, "inMarket": false, "lockedStatus": false, "title": "Five-SeveN | Berries And Cherries (Factory New)", "status": "active", "dm_discount": 16, "dm_price": {"value": 25.31, "currency": "USD", "cValue": null, "cCurrency": null}, "sm_price": null, "steam_name_id": "176209175", "histogram": null}, {"itemId": "188530139:4614852051:27849503443:730", "amount": 1, "inMarket": false, "lockedStatus": false, "title": "AK-47 | Orbit Mk01 (Field-Tested)", "status": "active", "dm_discount": 16, "dm_price": {"value": 7.09, "currency": "USD", "cValue": null, "cCurrency": null}, "sm_price": null, "steam_name_id": "175896286", "histogram": null}, {"itemId": "188530139:4141779994:27863466759:730", "amount": 1, "inMarket": false, "lockedStatus": false, "title": "Glock-18 | Neo-Noir (Well-Worn)", "status": "active", "dm_discount": 16, "dm_price": {"value": 5.05, "currency": "USD", "cValue": null, "cCurrency": null}, "sm_price": null, "steam_name_id": "176209458", "histogram": null}, {"itemId": "188530139:4428828851:27863602391:730", "amount": 1, "inMarket": false, "lockedStatus": false, "title": "USP-S | The Traitor (Well-Worn)", "status": "active", "dm_discount": 16, "dm_price": {"value": 9.18, "currency": "USD", "cValue": null, "cCurrency": null}, "sm_price": null, "steam_name_id": "176241049", "histogram": null}, {"itemId": "480085569:1311777481:27806440179:730", "amount": 1, "inMarket": false, "lockedStatus": false, "title": "M4A1-S | Golden Coil (Well-Worn)", "status": "active", "dm_discount": 16, "dm_price": {"value": 26.92, "currency": "USD", "cValue": null, "cCurrency": null}, "sm_price": null, "steam_name_id": "67061032", "histogram": null}, {"itemId": "188530170:520041153:27851288457:730", "amount": 1, "inMarket": false, "lockedStatus": false, "title": "StatTrak\u2122 Glock-18 | Water Elemental (Field-Tested)", "status": "active", "dm_discount": 16, "dm_price": {"value": 8.82, "currency": "USD", "cValue": null, "cCurrency": null}, "sm_price": null, "steam_name_id": "14963017", "histogram": null}, {"itemId": "480085569:5098027355:27862342468:730", "amount": 1, "inMarket": false, "lockedStatus": false, "title": "USP-S | The Traitor (Well-Worn)", "status": "active", "dm_discount": 16, "dm_price": {"value": 9.2, "currency": "USD", "cValue": null, "cCurrency": null}, "sm_price": null, "steam_name_id": "176241049", "histogram": null}, {"itemId": "188530170:5096680686:27853061112:730", "amount": 1, "inMarket": false, "lockedStatus": false, "title": "StatTrak\u2122 AK-47 | Legion of Anubis (Minimal Wear)", "status": "active", "dm_discount": 16, "dm_price": {"value": 30.0, "currency": "USD", "cValue": null, "cCurrency": null}, "sm_price": null, "steam_name_id": "176185949", "histogram": null}, {"itemId": "902658099:3114107362:27846067806:730", "amount": 1, "inMarket": false, "lockedStatus": false, "title": "StatTrak\u2122 Desert Eagle | Mecha Industries (Factory New)", "status": "active", "dm_discount": 16, "dm_price": {"value": 15.73, "currency": "USD", "cValue": null, "cCurrency": null}, "sm_price": null, "steam_name_id": "176024810", "histogram": null}, {"itemId": "188530139:4910488438:27862248216:730", "amount": 1, "inMarket": false, "lockedStatus": false, "title": "AK-47 | Ice Coaled (Battle-Scarred)", "status": "active", "dm_discount": 15, "dm_price": {"value": 8.56, "currency": "USD", "cValue": null, "cCurrency": null}, "sm_price": null, "steam_name_id": "176321231", "histogram": null}, {"itemId": "188530139:2967421436:27858527389:730", "amount": 1, "inMarket": false, "lockedStatus": false, "title": "\u2605 Navaja Knife | Case Hardened (Minimal Wear)", "status": "active", "dm_discount": 15, "dm_price": {"value": 76.81, "currency": "USD", "cValue": null, "cCurrency": null}, "sm_price": null, "steam_name_id": "176000106", "histogram": null}, {"itemId": "188530139:4579887867:27863268557:730", "amount": 1, "inMarket": false, "lockedStatus": false, "title": "AK-47 | Neon Revolution (Field-Tested)", "status": "active", "dm_discount": 15, "dm_price": {"value": 12.6, "currency": "USD", "cValue": null, "cCurrency": null}, "sm_price": null, "steam_name_id": "165031020", "histogram": null}, {"itemId": "188530170:4916897495:27850510842:730", "amount": 1, "inMarket": false, "lockedStatus": false, "title": "StatTrak\u2122 AK-47 | Phantom Disruptor (Factory New)", "status": "active", "dm_discount": 15, "dm_price": {"value": 24.59, "currency": "USD", "cValue": null, "cCurrency": null}, "sm_price": null, "steam_name_id": "176118353", "histogram": null}, {"itemId": "188530170:4743349507:27866298908:730", "amount": 1, "inMarket": false, "lockedStatus": false, "title": "StatTrak\u2122 Five-SeveN | Case Hardened (Battle-Scarred)", "status": "active", "dm_discount": 15, "dm_price": {"value": 7.29, "currency": "USD", "cValue": null, "cCurrency": null}, "sm_price": null, "steam_name_id": "1917968", "histogram": null}, {"itemId": "188530139:4864701307:27864156267:730", "amount": 1, "inMarket": false, "lockedStatus": false, "title": "M4A1-S | Nightmare (Well-Worn)", "status": "active", "dm_discount": 15, "dm_price": {"value": 6.41, "currency": "USD", "cValue": null, "cCurrency": null}, "sm_price": null, "steam_name_id": "175999991", "histogram": null}, {"itemId": "480085569:5098264332:27862296608:730", "amount": 1, "inMarket": false, "lockedStatus": false, "title": "AK-47 | Orbit Mk01 (Minimal Wear)", "status": "active", "dm_discount": 15, "dm_price": {"value": 8.35, "currency": "USD", "cValue": null, "cCurrency": null}, "sm_price": null, "steam_name_id": "175896327", "histogram": null}, {"itemId": "188530170:1813163924:27862302354:730", "amount": 1, "inMarket": false, "lockedStatus": false, "title": "StatTrak\u2122 M4A1-S | Mecha Industries (Field-Tested)", "status": "active", "dm_discount": 15, "dm_price": {"value": 37.52, "currency": "USD", "cValue": null, "cCurrency": null}, "sm_price": null, "steam_name_id": "156117105", "histogram": null}, {"itemId": "188530170:4917374702:27854052384:730", "amount": 1, "inMarket": false, "lockedStatus": false, "title": "StatTrak\u2122 M4A1-S | Mecha Industries (Field-Tested)", "status": "active", "dm_discount": 15, "dm_price": {"value": 37.52, "currency": "USD", "cValue": null, "cCurrency": null}, "sm_price": null, "steam_name_id": "156117105", "histogram": null}, {"itemId": "188530170:5057330141:27845197591:730", "amount": 1, "inMarket": false, "lockedStatus": false, "title": "StatTrak\u2122 M4A1-S | Mecha Industries (Field-Tested)", "status": "active", "dm_discount": 15, "dm_price": {"value": 37.52, "currency": "USD", "cValue": null, "cCurrency": null}, "sm_price": null, "steam_name_id": "156117105", "histogram": null}, {"itemId": "188530326:4524518552:26292145748:730", "amount": 1, "inMarket": false, "lockedStatus": false, "title": "\u2605 StatTrak\u2122 Falchion Knife | Stained (Battle-Scarred)", "status": "active", "dm_discount": 15, "dm_price": {"value": 87.99, "currency": "USD", "cValue": null, "cCurrency": null}, "sm_price": null, "steam_name_id": "49612091", "histogram": null}, {"itemId": "188530170:311432750:27845482860:730", "amount": 1, "inMarket": false, "lockedStatus": false, "title": "StatTrak\u2122 M4A4 | X-Ray (Field-Tested)", "status": "active", "dm_discount": 15, "dm_price": {"value": 25.99, "currency": "USD", "cValue": null, "cCurrency": null}, "sm_price": null, "steam_name_id": "3469449", "histogram": null}, {"itemId": "188530139:4844126746:27750289022:730", "amount": 1, "inMarket": false, "lockedStatus": false, "title": "USP-S | Blueprint (Minimal Wear)", "status": "active", "dm_discount": 15, "dm_price": {"value": 7.71, "currency": "USD", "cValue": null, "cCurrency": null}, "sm_price": null, "steam_name_id": "175896307", "histogram": null}, {"itemId": "480085569:520027744:27851288466:730", "amount": 1, "inMarket": false, "lockedStatus": false, "title": "Desert Eagle | Conspiracy (Factory New)", "status": "active", "dm_discount": 15, "dm_price": {"value": 6.01, "currency": "USD", "cValue": null, "cCurrency": null}, "sm_price": null, "steam_name_id": "14962960", "histogram": null}, {"itemId": "188530139:3955268625:27870228559:730", "amount": 1, "inMarket": false, "lockedStatus": false, "title": "M4A4 | Tooth Fairy (Minimal Wear)", "status": "active", "dm_discount": 15, "dm_price": {"value": 5.05, "currency": "USD", "cValue": null, "cCurrency": null}, "sm_price": null, "steam_name_id": "176185939", "histogram": null}, {"itemId": "480085569:4726077814:27866447007:730", "amount": 1, "inMarket": false, "lockedStatus": false, "title": "MP9 | Starlight Protector (Field-Tested)", "status": "active", "dm_discount": 15, "dm_price": {"value": 5.86, "currency": "USD", "cValue": null, "cCurrency": null}, "sm_price": null, "steam_name_id": "176288507", "histogram": null}, {"itemId": "480085569:5092509093:27847595185:730", "amount": 1, "inMarket": false, "lockedStatus": false, "title": "M4A1-S | Hyper Beast (Battle-Scarred)", "status": "active", "dm_discount": 15, "dm_price": {"value": 10.51, "currency": "USD", "cValue": null, "cCurrency": null}, "sm_price": null, "steam_name_id": "40094827", "histogram": null}, {"itemId": "188530139:310778479:27849187153:730", "amount": 1, "inMarket": false, "lockedStatus": false, "title": "MP7 | Skulls (Field-Tested)", "status": "active", "dm_discount": 15, "dm_price": {"value": 10.26, "currency": "USD", "cValue": null, "cCurrency": null}, "sm_price": null, "steam_name_id": "1321334", "histogram": null}, {"itemId": "188530139:4850766303:25766515102:730", "amount": 1, "inMarket": false, "lockedStatus": false, "title": "USP-S | Monster Mashup (Minimal Wear)", "status": "active", "dm_discount": 15, "dm_price": {"value": 16.92, "currency": "USD", "cValue": null, "cCurrency": null}, "sm_price": null, "steam_name_id": "176209206", "histogram": null}, {"itemId": "188530170:4388433039:27846448671:730", "amount": 1, "inMarket": false, "lockedStatus": false, "title": "StatTrak\u2122 AK-47 | Blue Laminate (Minimal Wear)", "status": "active", "dm_discount": 15, "dm_price": {"value": 14.1, "currency": "USD", "cValue": null, "cCurrency": null}, "sm_price": null, "steam_name_id": "3441232", "histogram": null}, {"itemId": "188530139:5098022022:27868711236:730", "amount": 1, "inMarket": false, "lockedStatus": false, "title": "MP9 | Starlight Protector (Field-Tested)", "status": "active", "dm_discount": 15, "dm_price": {"value": 5.88, "currency": "USD", "cValue": null, "cCurrency": null}, "sm_price": null, "steam_name_id": "176288507", "histogram": null}, {"itemId": "480085569:4784154935:27792896321:730", "amount": 1, "inMarket": false, "lockedStatus": false, "title": "M4A1-S | Cyrex (Field-Tested)", "status": "active", "dm_discount": 15, "dm_price": {"value": 12.61, "currency": "USD", "cValue": null, "cCurrency": null}, "sm_price": null, "steam_name_id": "14962989", "histogram": null}, {"itemId": "902658099:3955322167:27859592567:730", "amount": 1, "inMarket": false, "lockedStatus": false, "title": "StatTrak\u2122 AK-47 | Legion of Anubis (Minimal Wear)", "status": "active", "dm_discount": 15, "dm_price": {"value": 30.25, "currency": "USD", "cValue": null, "cCurrency": null}, "sm_price": null, "steam_name_id": "176185949", "histogram": null}, {"itemId": "188530139:2566902015:26638353267:730", "amount": 1, "inMarket": false, "lockedStatus": false, "title": "M4A1-S | Hyper Beast (Well-Worn)", "status": "active", "dm_discount": 15, "dm_price": {"value": 13.29, "currency": "USD", "cValue": null, "cCurrency": null}, "sm_price": null, "steam_name_id": "40097839", "histogram": null}, {"itemId": "188530170:3771886429:27865617316:730", "amount": 1, "inMarket": false, "lockedStatus": false, "title": "StatTrak\u2122 M4A1-S | Player Two (Field-Tested)", "status": "active", "dm_discount": 15, "dm_price": {"value": 37.24, "currency": "USD", "cValue": null, "cCurrency": null}, "sm_price": null, "steam_name_id": "176118422", "histogram": null}, {"itemId": "188530139:4428770291:27865207249:730", "amount": 1, "inMarket": false, "lockedStatus": false, "title": "USP-S | The Traitor (Field-Tested)", "status": "active", "dm_discount": 15, "dm_price": {"value": 12.01, "currency": "USD", "cValue": null, "cCurrency": null}, "sm_price": null, "steam_name_id": "176241093", "histogram": null}, {"itemId": "188530139:4428770291:27853889906:730", "amount": 1, "inMarket": false, "lockedStatus": false, "title": "USP-S | The Traitor (Field-Tested)", "status": "active", "dm_discount": 15, "dm_price": {"value": 12.01, "currency": "USD", "cValue": null, "cCurrency": null}, "sm_price": null, "steam_name_id": "176241093", "histogram": null}, {"itemId": "188530170:5098199180:27866093603:730", "amount": 1, "inMarket": false, "lockedStatus": false, "title": "\u2605 StatTrak\u2122 Gut Knife | Rust Coat (Battle-Scarred)", "status": "active", "dm_discount": 15, "dm_price": {"value": 71.88, "currency": "USD", "cValue": null, "cCurrency": null}, "sm_price": null, "steam_name_id": "29455396", "histogram": null}, {"itemId": "188530139:5013442231:27846864802:730", "amount": 1, "inMarket": false, "lockedStatus": false, "title": "M4A1-S | Hyper Beast (Battle-Scarred)", "status": "active", "dm_discount": 15, "dm_price": {"value": 10.56, "currency": "USD", "cValue": null, "cCurrency": null}, "sm_price": null, "steam_name_id": "40094827", "histogram": null}, {"itemId": "302028390:469457057:27588668531:730", "amount": 1, "inMarket": false, "lockedStatus": false, "title": "AK-47 | Emerald Pinstripe (Field-Tested)", "status": "active", "dm_discount": 15, "dm_price": {"value": 5.18, "currency": "USD", "cValue": null, "cCurrency": null}, "sm_price": null, "steam_name_id": "8989555", "histogram": null}, {"itemId": "188530139:5062562453:27862516783:730", "amount": 1, "inMarket": false, "lockedStatus": false, "title": "AK-47 | Point Disarray (Minimal Wear)", "status": "active", "dm_discount": 15, "dm_price": {"value": 13.01, "currency": "USD", "cValue": null, "cCurrency": null}, "sm_price": null, "steam_name_id": "84454619", "histogram": null}, {"itemId": "902658099:1939504346:26973036772:730", "amount": 1, "inMarket": false, "lockedStatus": false, "title": "StatTrak\u2122 AK-47 | Neon Revolution (Factory New)", "status": "active", "dm_discount": 15, "dm_price": {"value": 95.6, "currency": "USD", "cValue": null, "cCurrency": null}, "sm_price": null, "steam_name_id": "165278770", "histogram": null}, {"itemId": "188530139:4910470216:26651054247:730", "amount": 1, "inMarket": false, "lockedStatus": false, "title": "AK-47 | Ice Coaled (Field-Tested)", "status": "active", "dm_discount": 15, "dm_price": {"value": 14.13, "currency": "USD", "cValue": null, "cCurrency": null}, "sm_price": null, "steam_name_id": "176321254", "histogram": null}, {"itemId": "188530139:4259122389:22871225037:730", "amount": 1, "inMarket": false, "lockedStatus": false, "title": "\u2605 Gut Knife | Case Hardened (Field-Tested)", "status": "active", "dm_discount": 15, "dm_price": {"value": 87.0, "currency": "USD", "cValue": null, "cCurrency": null}, "sm_price": null, "steam_name_id": "1331370", "histogram": null}, {"itemId": "188530139:4929593386:27849517562:730", "amount": 1, "inMarket": false, "lockedStatus": false, "title": "M4A1-S | Hyper Beast (Battle-Scarred)", "status": "active", "dm_discount": 15, "dm_price": {"value": 10.58, "currency": "USD", "cValue": null, "cCurrency": null}, "sm_price": null, "steam_name_id": "40094827", "histogram": null}, {"itemId": "480085569:4141883867:22667212540:730", "amount": 1, "inMarket": false, "lockedStatus": false, "title": "MAC-10 | Gold Brick (Factory New)", "status": "active", "dm_discount": 14, "dm_price": {"value": 28.0, "currency": "USD", "cValue": null, "cCurrency": null}, "sm_price": null, "steam_name_id": "176209526", "histogram": null}, {"itemId": "188530139:4151974878:27848659047:730", "amount": 1, "inMarket": false, "lockedStatus": false, "title": "AK-47 | The Empress (Battle-Scarred)", "status": "active", "dm_discount": 14, "dm_price": {"value": 15.0, "currency": "USD", "cValue": null, "cCurrency": null}, "sm_price": null, "steam_name_id": "175917396", "histogram": null}, {"itemId": "188530139:4578742331:27867826464:730", "amount": 1, "inMarket": false, "lockedStatus": false, "title": "\u2605 Shadow Daggers | Lore (Well-Worn)", "status": "active", "dm_discount": 14, "dm_price": {"value": 89.22, "currency": "USD", "cValue": null, "cCurrency": null}, "sm_price": null, "steam_name_id": "176263198", "histogram": null}, {"itemId": "188530139:937277640:27861027096:730", "amount": 1, "inMarket": false, "lockedStatus": false, "title": "M4A1-S | Hyper Beast (Battle-Scarred)", "status": "active", "dm_discount": 14, "dm_price": {"value": 10.59, "currency": "USD", "cValue": null, "cCurrency": null}, "sm_price": null, "steam_name_id": "40094827", "histogram": null}, {"itemId": "188530139:4723169956:27865198115:730", "amount": 1, "inMarket": false, "lockedStatus": false, "title": "\u2605 Falchion Knife | Forest DDPAT (Field-Tested)", "status": "active", "dm_discount": 14, "dm_price": {"value": 67.59, "currency": "USD", "cValue": null, "cCurrency": null}, "sm_price": null, "steam_name_id": "49430981", "histogram": null}, {"itemId": "188530139:5024975493:27851352643:730", "amount": 1, "inMarket": false, "lockedStatus": false, "title": "AK-47 | Point Disarray (Field-Tested)", "status": "active", "dm_discount": 14, "dm_price": {"value": 9.02, "currency": "USD", "cValue": null, "cCurrency": null}, "sm_price": null, "steam_name_id": "84444477", "histogram": null}, {"itemId": "188530139:520037948:27859474143:730", "amount": 1, "inMarket": false, "lockedStatus": false, "title": "M4A1-S | Cyrex (Well-Worn)", "status": "active", "dm_discount": 14, "dm_price": {"value": 11.85, "currency": "USD", "cValue": null, "cCurrency": null}, "sm_price": null, "steam_name_id": "14963014", "histogram": null}, {"itemId": "188530139:527651415:27853560511:730", "amount": 1, "inMarket": false, "lockedStatus": false, "title": "Desert Eagle | Crimson Web (Minimal Wear)", "status": "active", "dm_discount": 14, "dm_price": {"value": 15.65, "currency": "USD", "cValue": null, "cCurrency": null}, "sm_price": null, "steam_name_id": "15492603", "histogram": null}, {"itemId": "188530170:1815369251:27848507619:730", "amount": 1, "inMarket": false, "lockedStatus": false, "title": "StatTrak\u2122 Glock-18 | Wasteland Rebel (Field-Tested)", "status": "active", "dm_discount": 14, "dm_price": {"value": 10.05, "currency": "USD", "cValue": null, "cCurrency": null}, "sm_price": null, "steam_name_id": "156140148", "histogram": null}, {"itemId": "188530139:4625411176:27851288520:730", "amount": 1, "inMarket": false, "lockedStatus": false, "title": "Souvenir AK-47 | Green Laminate (Minimal Wear)", "status": "active", "dm_discount": 14, "dm_price": {"value": 9.6, "currency": "USD", "cValue": null, "cCurrency": null}, "sm_price": null, "steam_name_id": "176271233", "histogram": null}, {"itemId": "188530139:4910615021:27854605245:730", "amount": 1, "inMarket": false, "lockedStatus": false, "title": "AK-47 | Ice Coaled (Well-Worn)", "status": "active", "dm_discount": 14, "dm_price": {"value": 13.74, "currency": "USD", "cValue": null, "cCurrency": null}, "sm_price": null, "steam_name_id": "176321313", "histogram": null}, {"itemId": "188530139:310776528:27853744486:730", "amount": 1, "inMarket": false, "lockedStatus": false, "title": "USP-S | Overgrowth (Minimal Wear)", "status": "active", "dm_discount": 14, "dm_price": {"value": 19.62, "currency": "USD", "cValue": null, "cCurrency": null}, "sm_price": null, "steam_name_id": "1547689", "histogram": null}, {"itemId": "188530139:4578815851:27862724043:730", "amount": 1, "inMarket": false, "lockedStatus": false, "title": "\u2605 Huntsman Knife | Freehand (Field-Tested)", "status": "active", "dm_discount": 14, "dm_price": {"value": 90.26, "currency": "USD", "cValue": null, "cCurrency": null}, "sm_price": null, "steam_name_id": "176263200", "histogram": null}, {"itemId": "188530139:2222220873:27115779518:730", "amount": 1, "inMarket": false, "lockedStatus": false, "title": "\u2605 Bowie Knife | Damascus Steel (Field-Tested)", "status": "active", "dm_discount": 14, "dm_price": {"value": 93.0, "currency": "USD", "cValue": null, "cCurrency": null}, "sm_price": null, "steam_name_id": "175880668", "histogram": null}, {"itemId": "902658099:5068649564:27848203878:730", "amount": 1, "inMarket": false, "lockedStatus": false, "title": "StatTrak\u2122 MP9 | Rose Iron (Factory New)", "status": "active", "dm_discount": 14, "dm_price": {"value": 9.47, "currency": "USD", "cValue": null, "cCurrency": null}, "sm_price": null, "steam_name_id": "3450994", "histogram": null}, {"itemId": "188530139:4625401432:24337640523:730", "amount": 1, "inMarket": false, "lockedStatus": false, "title": "Souvenir P90 | Run and Hide (Battle-Scarred)", "status": "active", "dm_discount": 14, "dm_price": {"value": 13.34, "currency": "USD", "cValue": null, "cCurrency": null}, "sm_price": null, "steam_name_id": "176271408", "histogram": null}, {"itemId": "302028390:4252812208:27854608219:730", "amount": 1, "inMarket": false, "lockedStatus": false, "title": "MP7 | Fade (Factory New)", "status": "active", "dm_discount": 14, "dm_price": {"value": 7.46, "currency": "USD", "cValue": null, "cCurrency": null}, "sm_price": null, "steam_name_id": "176012409", "histogram": null}, {"itemId": "480085569:4726157063:27867074481:730", "amount": 1, "inMarket": false, "lockedStatus": false, "title": "AK-47 | Nightwish (Battle-Scarred)", "status": "active", "dm_discount": 14, "dm_price": {"value": 8.7, "currency": "USD", "cValue": null, "cCurrency": null}, "sm_price": null, "steam_name_id": "176288611", "histogram": null}, {"itemId": "188530139:4616374699:27858277481:730", "amount": 1, "inMarket": false, "lockedStatus": false, "title": "AK-47 | Neon Revolution (Battle-Scarred)", "status": "active", "dm_discount": 14, "dm_price": {"value": 11.25, "currency": "USD", "cValue": null, "cCurrency": null}, "sm_price": null, "steam_name_id": "165027696", "histogram": null}, {"itemId": "480085569:1440505637:27857217440:730", "amount": 1, "inMarket": false, "lockedStatus": false, "title": "AK-47 | Point Disarray (Field-Tested)", "status": "active", "dm_discount": 14, "dm_price": {"value": 9.05, "currency": "USD", "cValue": null, "cCurrency": null}, "sm_price": null, "steam_name_id": "84444477", "histogram": null}, {"itemId": "188530170:3957267804:27850067488:730", "amount": 1, "inMarket": false, "lockedStatus": false, "title": "StatTrak\u2122 M4A4 | Tooth Fairy (Well-Worn)", "status": "active", "dm_discount": 14, "dm_price": {"value": 5.14, "currency": "USD", "cValue": null, "cCurrency": null}, "sm_price": null, "steam_name_id": "176186199", "histogram": null}, {"itemId": "188530139:5098026367:27866934098:730", "amount": 1, "inMarket": false, "lockedStatus": false, "title": "P250 | Visions (Minimal Wear)", "status": "active", "dm_discount": 14, "dm_price": {"value": 9.41, "currency": "USD", "cValue": null, "cCurrency": null}, "sm_price": null, "steam_name_id": "176321219", "histogram": null}, {"itemId": "188530139:4578775042:27854007317:730", "amount": 1, "inMarket": false, "lockedStatus": false, "title": "\u2605 Bowie Knife | Bright Water (Field-Tested)", "status": "active", "dm_discount": 14, "dm_price": {"value": 85.82, "currency": "USD", "cValue": null, "cCurrency": null}, "sm_price": null, "steam_name_id": "176263235", "histogram": null}, {"itemId": "188530170:4910501930:27859394892:730", "amount": 1, "inMarket": false, "lockedStatus": false, "title": "StatTrak\u2122 P250 | Visions (Field-Tested)", "status": "active", "dm_discount": 14, "dm_price": {"value": 9.51, "currency": "USD", "cValue": null, "cCurrency": null}, "sm_price": null, "steam_name_id": "176321324", "histogram": null}, {"itemId": "188530170:1704578786:27850683750:730", "amount": 1, "inMarket": false, "lockedStatus": false, "title": "StatTrak\u2122 M4A1-S | Chantico's Fire (Field-Tested)", "status": "active", "dm_discount": 14, "dm_price": {"value": 39.7, "currency": "USD", "cValue": null, "cCurrency": null}, "sm_price": null, "steam_name_id": "149892596", "histogram": null}, {"itemId": "188530170:4845842146:27846656993:730", "amount": 1, "inMarket": false, "lockedStatus": false, "title": "StatTrak\u2122 AK-47 | Slate (Field-Tested)", "status": "active", "dm_discount": 14, "dm_price": {"value": 7.82, "currency": "USD", "cValue": null, "cCurrency": null}, "sm_price": null, "steam_name_id": "176240990", "histogram": null}, {"itemId": "188530139:5003399588:27795112296:730", "amount": 1, "inMarket": false, "lockedStatus": false, "title": "AK-47 | Nightwish (Minimal Wear)", "status": "active", "dm_discount": 14, "dm_price": {"value": 45.0, "currency": "USD", "cValue": null, "cCurrency": null}, "sm_price": null, "steam_name_id": "176288589", "histogram": null}, {"itemId": "902658099:3574269111:27854383415:730", "amount": 1, "inMarket": false, "lockedStatus": false, "title": "StatTrak\u2122 FAMAS | Commemoration (Minimal Wear)", "status": "active", "dm_discount": 14, "dm_price": {"value": 31.31, "currency": "USD", "cValue": null, "cCurrency": null}, "sm_price": null, "steam_name_id": "176091939", "histogram": null}, {"itemId": "188530139:1818150636:27845476454:730", "amount": 1, "inMarket": false, "lockedStatus": false, "title": "\u2605 Gut Knife | Bright Water (Minimal Wear)", "status": "active", "dm_discount": 14, "dm_price": {"value": 77.08, "currency": "USD", "cValue": null, "cCurrency": null}, "sm_price": null, "steam_name_id": "156280279", "histogram": null}, {"itemId": "188530139:1560441601:27854315261:730", "amount": 1, "inMarket": false, "lockedStatus": false, "title": "Desert Eagle | Kumicho Dragon (Battle-Scarred)", "status": "active", "dm_discount": 14, "dm_price": {"value": 7.33, "currency": "USD", "cValue": null, "cCurrency": null}, "sm_price": null, "steam_name_id": "139673200", "histogram": null}, {"itemId": "188530139:310776531:27854390879:730", "amount": 1, "inMarket": false, "lockedStatus": false, "title": "AK-47 | Blue Laminate (Factory New)", "status": "active", "dm_discount": 14, "dm_price": {"value": 7.91, "currency": "USD", "cValue": null, "cCurrency": null}, "sm_price": null, "steam_name_id": "3440920", "histogram": null}, {"itemId": "188530139:3955317693:27846657001:730", "amount": 1, "inMarket": false, "lockedStatus": false, "title": "AK-47 | Legion of Anubis (Minimal Wear)", "status": "active", "dm_discount": 14, "dm_price": {"value": 11.68, "currency": "USD", "cValue": null, "cCurrency": null}, "sm_price": null, "steam_name_id": "176186016", "histogram": null}, {"itemId": "188530170:3016076939:27628315874:730", "amount": 1, "inMarket": false, "lockedStatus": false, "title": "\u2605 StatTrak\u2122 Ursus Knife | Forest DDPAT (Battle-Scarred)", "status": "active", "dm_discount": 14, "dm_price": {"value": 82.11, "currency": "USD", "cValue": null, "cCurrency": null}, "sm_price": null, "steam_name_id": "176009887", "histogram": null}, {"itemId": "188530139:3097771661:25590920792:730", "amount": 1, "inMarket": false, "lockedStatus": false, "title": "AK-47 | Aquamarine Revenge (Field-Tested)", "status": "active", "dm_discount": 14, "dm_price": {"value": 21.0, "currency": "USD", "cValue": null, "cCurrency": null}, "sm_price": null, "steam_name_id": "49399542", "histogram": null}, {"itemId": "188530139:1012391026:27329336528:730", "amount": 1, "inMarket": false, "lockedStatus": false, "title": "\u2605 Falchion Knife | Night (Field-Tested)", "status": "active", "dm_discount": 14, "dm_price": {"value": 79.78, "currency": "USD", "cValue": null, "cCurrency": null}, "sm_price": null, "steam_name_id": "49399565", "histogram": null}, {"itemId": "188530170:4579687894:27863750173:730", "amount": 1, "inMarket": false, "lockedStatus": false, "title": "\u2605 StatTrak\u2122 Huntsman Knife | Bright Water (Field-Tested)", "status": "active", "dm_discount": 14, "dm_price": {"value": 85.35, "currency": "USD", "cValue": null, "cCurrency": null}, "sm_price": null, "steam_name_id": "176263365", "histogram": null}, {"itemId": "902658099:2736563565:27866131989:730", "amount": 1, "inMarket": false, "lockedStatus": false, "title": "StatTrak\u2122 AUG | Stymphalian (Factory New)", "status": "active", "dm_discount": 14, "dm_price": {"value": 11.92, "currency": "USD", "cValue": null, "cCurrency": null}, "sm_price": null, "steam_name_id": "175967058", "histogram": null}, {"itemId": "188530139:4910487338:27854052390:730", "amount": 1, "inMarket": false, "lockedStatus": false, "title": "Sawed-Off | Kiss\u2665Love (Minimal Wear)", "status": "active", "dm_discount": 14, "dm_price": {"value": 9.68, "currency": "USD", "cValue": null, "cCurrency": null}, "sm_price": null, "steam_name_id": "176321242", "histogram": null}, {"itemId": "188530139:4989639054:27867921182:730", "amount": 1, "inMarket": false, "lockedStatus": false, "title": "Glock-18 | Neo-Noir (Field-Tested)", "status": "active", "dm_discount": 14, "dm_price": {"value": 7.04, "currency": "USD", "cValue": null, "cCurrency": null}, "sm_price": null, "steam_name_id": "176209329", "histogram": null}, {"itemId": "188530170:2531852646:27858453049:730", "amount": 1, "inMarket": false, "lockedStatus": false, "title": "StatTrak\u2122 M4A1-S | Leaded Glass (Field-Tested)", "status": "active", "dm_discount": 14, "dm_price": {"value": 9.35, "currency": "USD", "cValue": null, "cCurrency": null}, "sm_price": null, "steam_name_id": "175917346", "histogram": null}, {"itemId": "188530139:470644141:27854543769:730", "amount": 1, "inMarket": false, "lockedStatus": false, "title": "\u2605 Huntsman Knife | Forest DDPAT (Well-Worn)", "status": "active", "dm_discount": 14, "dm_price": {"value": 72.13, "currency": "USD", "cValue": null, "cCurrency": null}, "sm_price": null, "steam_name_id": "9007048", "histogram": null}, {"itemId": "188530139:4619148667:27852656153:730", "amount": 1, "inMarket": false, "lockedStatus": false, "title": "Desert Eagle | Crimson Web (Minimal Wear)", "status": "active", "dm_discount": 14, "dm_price": {"value": 15.78, "currency": "USD", "cValue": null, "cCurrency": null}, "sm_price": null, "steam_name_id": "15492603", "histogram": null}, {"itemId": "480085569:4141779258:27849954567:730", "amount": 1, "inMarket": false, "lockedStatus": false, "title": "Glock-18 | Neo-Noir (Field-Tested)", "status": "active", "dm_discount": 14, "dm_price": {"value": 7.04, "currency": "USD", "cValue": null, "cCurrency": null}, "sm_price": null, "steam_name_id": "176209329", "histogram": null}, {"itemId": "188530139:3859855419:27855430776:730", "amount": 1, "inMarket": false, "lockedStatus": false, "title": "AK-47 | Redline (Field-Tested)", "status": "active", "dm_discount": 14, "dm_price": {"value": 11.92, "currency": "USD", "cValue": null, "cCurrency": null}, "sm_price": null, "steam_name_id": "7178002", "histogram": null}, {"itemId": "480085569:4322287232:27859762754:730", "amount": 1, "inMarket": false, "lockedStatus": false, "title": "AK-47 | Blue Laminate (Factory New)", "status": "active", "dm_discount": 14, "dm_price": {"value": 7.93, "currency": "USD", "cValue": null, "cCurrency": null}, "sm_price": null, "steam_name_id": "3440920", "histogram": null}], "sortType": null, "sortDir": null, "priceFrom": 500, "priceTo": 10000, "lastCursor": "WzE0LjA4LDE2NzA3MTAwMDEwMDAsIjM1YzIwYWJmLTg3NzUtNGJmMS05MTViLTIyNjA5ZjIzZTk0MCJd", "done": null, "flags": [0, 1]}